src/__init__.py
src/core/__init__.py
src/core/engine.py
pytobf_muriloopr-1.0.0.dist-info/METADATA
pytobf_muriloopr-1.0.0.dist-info/WHEEL
pytobf_muriloopr-1.0.0.dist-info/entry_points.txt
pytobf_muriloopr-1.0.0.dist-info/top_level.txt
pytobf_muriloopr-1.0.0.dist-info/RECORD
