Metadata-Version: 2.4
Name: pytobf-muriloopr
Version: 1.0.0
Summary: A sacred transpiler from Python to Brainfuck
Author: MurilooPrDev
Requires-Python: >=3.6
Dynamic: author
Dynamic: requires-python
Dynamic: summary
